{"type":"object","required":["items"],"properties":{"items":{"type":"array","items":{"type":"object","required":["spec"],"properties":{"metadata":{"type":"object","properties":{"annotations":{"type":"object","items":{"type":"string"},"additionalProperties":true},"creationTimestamp":{"type":"string"},"deletionGracePeriodSeconds":{"type":"integer"},"deletionTimestamp":{"type":"string"},"finalizers":{"type":"array","items":{"type":"string"},"patchStrategy":"merge"},"generateName":{"type":"string"},"generation":{"type":"integer"},"labels":{"type":"object","items":{"type":"string"},"additionalProperties":true},"managedFields":{"type":"array","items":{"type":"object","properties":{"apiVersion":{"type":"string"},"fieldsType":{"type":"string"},"fieldsV1":{"type":"object"},"manager":{"type":"string"},"operation":{"type":"string"},"subresource":{"type":"string"},"time":{"type":"string"}}}},"name":{"type":"string"},"namespace":{"type":"string"},"ownerReferences":{"type":"array","items":{"type":"object","required":["apiVersion","kind","name","uid"],"properties":{"apiVersion":{"type":"string"},"blockOwnerDeletion":{"type":"boolean"},"controller":{"type":"boolean"},"kind":{"type":"string"},"name":{"type":"string"},"uid":{"type":"string"}}},"patchStrategy":"merge","patchMergeKey":"uid"},"resourceVersion":{"type":"string"},"selfLink":{"type":"string"},"uid":{"type":"string"}}},"spec":{"type":"object","required":["devices"],"properties":{"devices":{"type":"object","required":["requests"],"properties":{"config":{"type":"array","items":{"type":"object","properties":{"requests":{"type":"array","items":{"type":"string"}}}}},"constraints":{"type":"array","items":{"type":"object","properties":{"matchAttribute":{"type":"string"},"requests":{"type":"array","items":{"type":"string"}}}}},"requests":{"type":"array","items":{"type":"object","required":["name","deviceClassName"],"properties":{"adminAccess":{"type":"boolean"},"allocationMode":{"type":"string"},"count":{"type":"integer"},"deviceClassName":{"type":"string"},"firstAvailable":{"type":"array","items":{"type":"object","required":["name","deviceClassName"],"properties":{"allocationMode":{"type":"string"},"count":{"type":"integer"},"deviceClassName":{"type":"string"},"name":{"type":"string"},"selectors":{"type":"array","items":{"type":"object","properties":{"cel":{"type":"object","required":["expression"],"properties":{"expression":{"type":"string"}}}}}},"tolerations":{"type":"array","items":{"type":"object","properties":{"effect":{"type":"string"},"key":{"type":"string"},"operator":{"type":"string"},"tolerationSeconds":{"type":"integer"},"value":{"type":"string"}}}}}}},"name":{"type":"string"},"selectors":{"type":"array","items":{"type":"object","properties":{"cel":{"type":"object","required":["expression"],"properties":{"expression":{"type":"string"}}}}}},"tolerations":{"type":"array","items":{"type":"object","properties":{"effect":{"type":"string"},"key":{"type":"string"},"operator":{"type":"string"},"tolerationSeconds":{"type":"integer"},"value":{"type":"string"}}}}}}}}}}},"status":{"type":"object","properties":{"allocation":{"type":"object","properties":{"devices":{"type":"object","properties":{"config":{"type":"array","items":{"type":"object","required":["source"],"properties":{"requests":{"type":"array","items":{"type":"string"}},"source":{"type":"string"}}}},"results":{"type":"array","items":{"type":"object","required":["request","driver","pool","device","adminAccess"],"properties":{"adminAccess":{"type":"boolean"},"device":{"type":"string"},"driver":{"type":"string"},"pool":{"type":"string"},"request":{"type":"string"},"tolerations":{"type":"array","items":{"type":"object","properties":{"effect":{"type":"string"},"key":{"type":"string"},"operator":{"type":"string"},"tolerationSeconds":{"type":"integer"},"value":{"type":"string"}}}}}}}}},"nodeSelector":{"type":"object","required":["nodeSelectorTerms"],"properties":{"nodeSelectorTerms":{"type":"array","items":{"type":"object","properties":{"matchExpressions":{"type":"array","items":{"type":"object","required":["key","operator"],"properties":{"key":{"type":"string"},"operator":{"type":"string"},"values":{"type":"array","items":{"type":"string"}}}}},"matchFields":{"type":"array","items":{"type":"object","required":["key","operator"],"properties":{"key":{"type":"string"},"operator":{"type":"string"},"values":{"type":"array","items":{"type":"string"}}}}}}}}}}}},"devices":{"type":"array","items":{"type":"object","required":["driver","pool","device","conditions"],"properties":{"conditions":{"type":"array","items":{"type":"object","required":["type","status","lastTransitionTime","reason","message"],"properties":{"lastTransitionTime":{"type":"string"},"message":{"type":"string"},"observedGeneration":{"type":"integer"},"reason":{"type":"string"},"status":{"type":"string"},"type":{"type":"string"}}}},"data":{"type":"object"},"device":{"type":"string"},"driver":{"type":"string"},"networkData":{"type":"object","properties":{"hardwareAddress":{"type":"string"},"interfaceName":{"type":"string"},"ips":{"type":"array","items":{"type":"string"}}}},"pool":{"type":"string"}}}},"reservedFor":{"type":"array","items":{"type":"object","required":["resource","name","uid"],"properties":{"apiGroup":{"type":"string"},"name":{"type":"string"},"resource":{"type":"string"},"uid":{"type":"string"}}},"patchStrategy":"merge","patchMergeKey":"uid"}}}}}},"metadata":{"type":"object","properties":{"continue":{"type":"string"},"remainingItemCount":{"type":"integer"},"resourceVersion":{"type":"string"},"selfLink":{"type":"string"}}}}}
