{"type":"object","required":["groups"],"properties":{"groups":{"type":"array","items":{"type":"object","required":["name","versions"],"properties":{"name":{"type":"string"},"preferredVersion":{"type":"object","required":["groupVersion","version"],"properties":{"groupVersion":{"type":"string"},"version":{"type":"string"}}},"serverAddressByClientCIDRs":{"type":"array","items":{"type":"object","required":["clientCIDR","serverAddress"],"properties":{"clientCIDR":{"type":"string"},"serverAddress":{"type":"string"}}}},"versions":{"type":"array","items":{"type":"object","required":["groupVersion","version"],"properties":{"groupVersion":{"type":"string"},"version":{"type":"string"}}}}}}}}}
